packify/__init__.py
packify/errors.py
packify/interface.py
packify/serialization.py
packify-0.3.1.dist-info/METADATA
packify-0.3.1.dist-info/WHEEL
packify-0.3.1.dist-info/RECORD
