Metadata-Version: 2.4
Name: packify
Version: 0.3.1
Summary: Serialize and deserialize almost anything easily.
Project-URL: Homepage, https://github.com/k98kurz/packify
Project-URL: Bug Tracker, https://github.com/k98kurz/packify/issues
Author-email: k98kurz <k98kurz@gmail.com>
Classifier: Development Status :: 4 - Beta
Classifier: License :: OSI Approved :: ISC License (ISCL)
Classifier: Operating System :: OS Independent
Classifier: Programming Language :: Python :: 3
Classifier: Topic :: Software Development :: Libraries
Requires-Python: >=3.9
